django_tabination-0.4.0.dist-info/DESCRIPTION.rst
django_tabination-0.4.0.dist-info/RECORD
django_tabination-0.4.0.dist-info/metadata.json
django_tabination-0.4.0.dist-info/METADATA
django_tabination-0.4.0.dist-info/top_level.txt
django_tabination-0.4.0.dist-info/WHEEL
tabination/__init__.py
tabination/dummy_settings.py
tabination/views.py
tabination/test_urls.py
tabination/test_settings.py
tabination/models.py
